xarray_einstats/__init__.py
xarray_einstats/__init__.pyi
xarray_einstats/accessors.py
xarray_einstats/accessors.pyi
xarray_einstats/einops.py
xarray_einstats/einops.pyi
xarray_einstats/linalg.py
xarray_einstats/linalg.pyi
xarray_einstats/numba.py
xarray_einstats/numba.pyi
xarray_einstats/py.typed
xarray_einstats/stats.py
xarray_einstats/stats.pyi
xarray_einstats/tutorial.py
xarray_einstats/tutorial.pyi
xarray_einstats-0.9.0.dist-info/licenses/LICENSE
xarray_einstats-0.9.0.dist-info/WHEEL
xarray_einstats-0.9.0.dist-info/METADATA
xarray_einstats-0.9.0.dist-info/RECORD
