Metadata-Version: 2.4
Name: xarray-einstats
Version: 0.9.0
Summary: Stats, linear algebra and einops for xarray
Author-email: ArviZ team <arviz.devs@gmail.com>
Requires-Python: >=3.11
Classifier: Development Status :: 3 - Alpha
Classifier: Intended Audience :: Developers
Classifier: Intended Audience :: Science/Research
Classifier: Intended Audience :: Education
Classifier: License :: OSI Approved :: Apache Software License
Classifier: Operating System :: OS Independent
Classifier: Programming Language :: Python
Classifier: Programming Language :: Python :: 3
Classifier: Programming Language :: Python :: 3.11
Classifier: Programming Language :: Python :: 3.12
Classifier: Programming Language :: Python :: 3.13
Classifier: Programming Language :: Python :: 3.14
License-File: LICENSE
Requires-Dist: numpy>=1.25
Requires-Dist: scipy>=1.11
Requires-Dist: xarray>=2023.06.0
Requires-Dist: furo ; extra == "doc"
Requires-Dist: myst-parser[linkify] ; extra == "doc"
Requires-Dist: myst-nb ; extra == "doc"
Requires-Dist: sphinx-copybutton ; extra == "doc"
Requires-Dist: numpydoc ; extra == "doc"
Requires-Dist: sphinx>=5 ; extra == "doc"
Requires-Dist: jupyter-sphinx ; extra == "doc"
Requires-Dist: sphinx-design ; extra == "doc"
Requires-Dist: watermark ; extra == "doc"
Requires-Dist: matplotlib ; extra == "doc"
Requires-Dist: sphinx-togglebutton ; extra == "doc"
Requires-Dist: einops ; extra == "einops"
Requires-Dist: numba>=0.55 ; extra == "numba"
Requires-Dist: hypothesis ; extra == "test"
Requires-Dist: pytest ; extra == "test"
Requires-Dist: pytest-cov ; extra == "test"
Requires-Dist: packaging ; extra == "test"
Requires-Dist: scipy>=1.15 ; extra == "test"
Requires-Dist: preliz>=0.19 ; extra == "test"
Project-URL: documentation, https://xarray-einstats.readthedocs.io
Project-URL: funding, https://opencollective.com/arviz
Project-URL: source, https://github.com/arviz-devs/xarray-einstats
Project-URL: tracker, https://github.com/arviz-devs/xarray-einstats/issues
Provides-Extra: doc
Provides-Extra: einops
Provides-Extra: numba
Provides-Extra: test
